README.md
setup.py
tools_py/__init__.py
tools_py/common_tools.py
tools_py/timer_tools.py
tools_py.egg-info/PKG-INFO
tools_py.egg-info/SOURCES.txt
tools_py.egg-info/dependency_links.txt
tools_py.egg-info/top_level.txt