Metadata-Version: 2.1
Name: tools-py
Version: 1.0.1
Summary: 一些开发常用的函数
Home-page: https://github.com/xhatt/tools_py
Author: xhz
Author-email: 1269146988@qq.com
License: UNKNOWN
Platform: UNKNOWN
